{
    "scheduleOption": 0,
    "dataType": 0,
    "description": "",
    "appliesTo": "true()",
    "technology": "",
    "type": "propertyrule",
    "params": [
        {
            "name": "linuxcmdline",
            "comment": "",
            "value": ""
        },
        {
            "name": "linuxscript",
            "comment": "",
            "value": ""
        },
        {
            "name": "scriptgroovy",
            "comment": "",
            "value": "def companyId = hostProps.get('company.id')\n\nprintln \"auto.company.id=${companyId}\""
        },
        {
            "name": "scripttype",
            "comment": "embed",
            "value": "embed"
        },
        {
            "name": "windowscmdline",
            "comment": "",
            "value": ""
        },
        {
            "name": "windowsscript",
            "comment": "",
            "value": ""
        }
    ],
    "version": 1598974123,
    "tags": "",
    "auditVersion": 0,
    "name": "LogicMonitor_Company_ID",
    "id": 172,
    "group": "RFA Custom"
}